EmberJsCankaoWendang/README.md
EmberJsCankaoWendang/__init__.py
EmberJsCankaoWendang/__main__.py
EmberJsCankaoWendang/file.epub
EmberJsCankaoWendang/index.html
EmberJsCankaoWendang/css/__init__.py
EmberJsCankaoWendang/css/annotations.css
EmberJsCankaoWendang/css/main.css
EmberJsCankaoWendang/css/normalize.css
EmberJsCankaoWendang/css/popup.css
EmberJsCankaoWendang/font/__init__.py
EmberJsCankaoWendang/font/fontello.eot
EmberJsCankaoWendang/font/fontello.svg
EmberJsCankaoWendang/font/fontello.ttf
EmberJsCankaoWendang/font/fontello.woff
EmberJsCankaoWendang/img/__init__.py
EmberJsCankaoWendang/img/annotator-glyph-sprite.png
EmberJsCankaoWendang/img/annotator-icon-sprite.png
EmberJsCankaoWendang/img/apple-touch-icon.png
EmberJsCankaoWendang/img/cancelfullscreen.png
EmberJsCankaoWendang/img/close.png
EmberJsCankaoWendang/img/fullscreen.png
EmberJsCankaoWendang/img/loader.gif
EmberJsCankaoWendang/img/menu-icon.png
EmberJsCankaoWendang/img/save.png
EmberJsCankaoWendang/img/saved.png
EmberJsCankaoWendang/img/settings-s.png
EmberJsCankaoWendang/img/settings.png
EmberJsCankaoWendang/img/star.png
EmberJsCankaoWendang/js/__init__.py
EmberJsCankaoWendang/js/epub.js
EmberJsCankaoWendang/js/epub.min.js
EmberJsCankaoWendang/js/epub.min.map
EmberJsCankaoWendang/js/hooks.min.js
EmberJsCankaoWendang/js/hooks.min.map
EmberJsCankaoWendang/js/reader.js
EmberJsCankaoWendang/js/reader.js.map
EmberJsCankaoWendang/js/reader.min.js
EmberJsCankaoWendang/js/reader.min.map
EmberJsCankaoWendang/js/hooks/__init__.py
EmberJsCankaoWendang/js/hooks/extensions/__init__.py
EmberJsCankaoWendang/js/hooks/extensions/highlight.js
EmberJsCankaoWendang/js/libs/__init__.py
EmberJsCankaoWendang/js/libs/jquery.min.js
EmberJsCankaoWendang/js/libs/localforage.min.js
EmberJsCankaoWendang/js/libs/screenfull.js
EmberJsCankaoWendang/js/libs/screenfull.min.js
EmberJsCankaoWendang/js/libs/zip.min.js
EmberJsCankaoWendang/js/plugins/__init__.py
EmberJsCankaoWendang/js/plugins/hypothesis.js
ember_js_cankao_wendang-2024.3.2.0.dist-info/METADATA
ember_js_cankao_wendang-2024.3.2.0.dist-info/WHEEL
ember_js_cankao_wendang-2024.3.2.0.dist-info/entry_points.txt
ember_js_cankao_wendang-2024.3.2.0.dist-info/top_level.txt
ember_js_cankao_wendang-2024.3.2.0.dist-info/RECORD
